README
setup.py
py_dom_xpath_redux.egg-info/PKG-INFO
py_dom_xpath_redux.egg-info/SOURCES.txt
py_dom_xpath_redux.egg-info/dependency_links.txt
py_dom_xpath_redux.egg-info/top_level.txt
xpath/__init__.py
xpath/exceptions.py
xpath/expr.py
xpath/parser.py
xpath/yappsrt.py
yapps2/parsedesc.py
yapps2/yapps2.py
yapps2/yappsrt.py