Metadata-Version: 1.0
Name: py-dom-xpath-redux
Version: 0.1.1
Summary: XPath for DOM trees
Home-page: https://github.com/macropin/py-dom-xpath-redux
Author: Andrew Cutler
Author-email: macropin@gmail.com
License: UNKNOWN
Platform: UNKNOWN
